custom_connector_example/README.md
custom_connector_example/__init__.py
custom_connector_example/constants.py
custom_connector_example/template.yml
custom_connector_example/handlers/__init__.py
custom_connector_example/handlers/client.py
custom_connector_example/handlers/configuration.py
custom_connector_example/handlers/lambda_handler.py
custom_connector_example/handlers/metadata.py
custom_connector_example/handlers/record.py
custom_connector_example/handlers/salesforce.py
custom_connector_example/handlers/validation.py
custom_connector_example/integ_test/__init__.py
custom_connector_example/integ_test/sales_generator.py
custom_connector_example/integ_test/sales_test_case.py
custom_connector_example/query/__init__.py
custom_connector_example/query/builder.py
custom_connector_example/query/visitor.py
custom_connector_example/salesforce-example-test-files/describe-connector-entity-validation-file.json
custom_connector_example/salesforce-example-test-files/describe-connector-validation-file.json
custom_connector_example/salesforce-example-test-files/list-entities-validation-file.json
custom_connector_example/salesforce-example-test-files/salesforce-insert-file.csv
custom_connector_example/salesforce-example-test-files/test-file-2.json
custom_connector_example/salesforce-example-test-files/test-file-3.json
custom_connector_example/salesforce-example-test-files/test-file.json
custom_connector_example/test/__init__.py
custom_connector_example/test/configuration_test.py
custom_connector_example/test/metadata_test.py
custom_connector_example/test/query_test.py
custom_connector_example/test/record_test.py
custom_connector_example/test/resources/describe_connector_configuration_request_valid.json
custom_connector_example/test/resources/describe_entity_request_invalid.json
custom_connector_example/test/resources/describe_entity_request_valid.json
custom_connector_example/test/resources/describe_sobject_server_response.json
custom_connector_sdk-1.0.5.dist-info/LICENSE
custom_connector_sdk-1.0.5.dist-info/METADATA
custom_connector_sdk-1.0.5.dist-info/WHEEL
custom_connector_sdk-1.0.5.dist-info/top_level.txt
custom_connector_sdk-1.0.5.dist-info/RECORD
